{"cameraMode":{"drawMode":0,"name":"Shaded","section":"Shading Mode"},"sceneLighting":true,"audioPlay":false,"sceneViewState":{"m_AlwaysRefresh":false,"showFog":true,"showSkybox":true,"showFlares":true,"showImageEffects":true,"showParticleSystems":true,"showVisualEffectGraphs":true,"m_FxEnabled":true},"in2DMode":false,"pivot":{"x":-0.3639257848262787,"y":1.2503126859664918,"z":-9.828696250915528},"rotation":{"x":0.1314959079027176,"y":0.042511798441410068,"z":-0.005644389893859625,"w":0.9903887510299683},"size":0.19831429421901704,"orthographic":false}